{
  "updatedAt": "2026-05-28",
  "skills": {
    "cc-roadmap": "5.9.0",
    "cc-next": "1.4.1",
    "cc-dev": "1.7.0",
    "cc-plan": "3.19.0",
    "cc-investigate": "1.15.0",
    "cc-do": "1.10.2",
    "cc-review": "2.14.0",
    "cc-pr-review": "1.8.0",
    "cc-pr-land": "1.4.1",
    "cc-check": "1.17.0",
    "cc-act": "1.16.0",
    "cc-spec-init": "1.4.1",
    "cc-simplify": "1.8.0"
  },
  "examples": [
    {
      "id": "pdca-loop",
      "readme": "docs/examples/pdca-loop/README.md",
      "root": "docs/examples/pdca-loop",
      "changeDir": "docs/examples/pdca-loop/changes/REQ-001-copy-invite-link",
      "covers": [
        "cc-roadmap",
        "cc-plan",
        "cc-do",
        "cc-check",
        "cc-act"
      ],
      "expectedShipMode": "create-pr"
    },
    {
      "id": "full-design-blocked",
      "readme": "docs/examples/full-design-blocked/README.md",
      "root": "docs/examples/full-design-blocked",
      "changeDir": "docs/examples/full-design-blocked/changes/REQ-002-bulk-invite-import",
      "covers": [
        "cc-roadmap",
        "cc-plan",
        "cc-do",
        "cc-check"
      ],
      "expectedShipMode": "none"
    },
    {
      "id": "local-handoff",
      "readme": "docs/examples/local-handoff/README.md",
      "root": "docs/examples/local-handoff",
      "changeDir": "docs/examples/local-handoff/changes/REQ-003-audit-log-export",
      "covers": [
        "cc-roadmap",
        "cc-plan",
        "cc-do",
        "cc-check",
        "cc-act"
      ],
      "expectedShipMode": "local-handoff"
    }
  ]
}
